SparkleLogging/__init__.py
SparkleLogging/plugins/DecoratorsTools.py
SparkleLogging/plugins/HttpHander.py
SparkleLogging/plugins/__init__.py
SparkleLogging/plugins/excHandler.py
SparkleLogging/plugins/exclogger.py
SparkleLogging/plugins/websocketHander.py
SparkleLogging/utils/__init__.py
SparkleLogging/utils/core.py
SparkleLogging/utils/getLog.py
SparkleLogging/utils/plugins_for_core.py
SparkleLogging-1.0.9.dist-info/METADATA
SparkleLogging-1.0.9.dist-info/WHEEL
SparkleLogging-1.0.9.dist-info/top_level.txt
SparkleLogging-1.0.9.dist-info/RECORD
