Metadata-Version: 2.1
Name: SparkleLogging
Version: 1.0.9
Summary: A logging library for Python
Home-page: https://github.com/KOKOMI12345/SparkleLogging
Author: 花火official
Author-email: 3072252442@qq.com
Classifier: Programming Language :: Python :: 3
Classifier: License :: OSI Approved :: MIT License
Classifier: Operating System :: OS Independent
Requires-Dist: requests
Requires-Dist: websockets
Requires-Dist: colorlog
Requires-Dist: httpx
